yarastorm/__init__.py
yarastorm/__main__.py
yarastorm/api.py
yarastorm/defs.py
yarastorm/svc.py
yarastorm/pkgproto/gormo.yara.yaml
yarastorm/pkgproto/storm/commands/gormo.yara.check.storm
yarastorm/pkgproto/storm/commands/gormo.yara.disable.storm
yarastorm/pkgproto/storm/commands/gormo.yara.enable.storm
yarastorm/pkgproto/storm/commands/gormo.yara.scan.storm
yarastorm/pkgproto/storm/modules/gormo.yara.ingest.storm
yarastorm/pkgproto/storm/modules/gormo.yara.lib.storm
yarastorm-0.1.0.dist-info/LICENSE
yarastorm-0.1.0.dist-info/METADATA
yarastorm-0.1.0.dist-info/WHEEL
yarastorm-0.1.0.dist-info/top_level.txt
yarastorm-0.1.0.dist-info/RECORD
