Metadata-Version: 2.1
Name: yarastorm
Version: 0.1.0
Summary: The yarastorm Python package
Author: John Gorman
License: MIT License
Project-URL: Homepage, https://github.com/gormaniac/yarastorm
Project-URL: Documentation, https://gormo.co/yarastorm/
Requires-Python: >=3.11
License-File: LICENSE
Requires-Dist: pyyaml (>=6.0)
Requires-Dist: stormlibpp (>=0.3.0)
